MANIFEST.in
setup.py
confine_controller.egg-info/PKG-INFO
confine_controller.egg-info/SOURCES.txt
confine_controller.egg-info/dependency_links.txt
confine_controller.egg-info/top_level.txt
controller/__init__.py
controller/api.py
controller/dashboard.py
controller/menu.py
controller/modules.py
controller/renderers.py
controller/serializers.py
controller/settings.py
controller/tasks.py
controller/tests.py
controller/urls.py
controller/admin/__init__.py
controller/admin/decorators.py
controller/admin/filters.py
controller/admin/helpers.py
controller/admin/options.py
controller/admin/tests.py
controller/admin/utils.py
controller/admin/widgets.py
controller/apps/__init__.py
controller/apps/api/__init__.py
controller/apps/api/exceptions.py
controller/apps/api/filters.py
controller/apps/api/generics.py
controller/apps/api/helpers.py
controller/apps/api/negotiation.py
controller/apps/api/options.py
controller/apps/api/renderers.py
controller/apps/api/serializers.py
controller/apps/api/tests.py
controller/apps/api/utils/__init__.py
controller/apps/api/utils/profiles.py
controller/apps/communitynetworks/__init__.py
controller/apps/communitynetworks/actions.py
controller/apps/communitynetworks/admin.py
controller/apps/communitynetworks/api.py
controller/apps/communitynetworks/models.py
controller/apps/communitynetworks/permissions.py
controller/apps/communitynetworks/serializers.py
controller/apps/communitynetworks/settings.py
controller/apps/communitynetworks/tests.py
controller/apps/communitynetworks/certs/cacert.org.pem
controller/apps/communitynetworks/migrations/0001_initial.py
controller/apps/communitynetworks/migrations/0002_auto__chg_field_cnhost_object_id.py
controller/apps/communitynetworks/migrations/0003_auto__add_unique_cnhost_cndb_uri.py
controller/apps/communitynetworks/migrations/0004_auto__chg_field_cnhost_cndb_uri.py
controller/apps/communitynetworks/migrations/0005_auto__chg_field_cnhost_cndb_uri.py
controller/apps/communitynetworks/migrations/__init__.py
controller/apps/firmware/__init__.py
controller/apps/firmware/actions.py
controller/apps/firmware/admin.py
controller/apps/firmware/api.py
